pytika/__init__.py
pytika/api.py
pytika/config.py
pytika/errors.py
pytika-0.2.0.dist-info/LICENSE
pytika-0.2.0.dist-info/WHEEL
pytika-0.2.0.dist-info/METADATA
pytika-0.2.0.dist-info/RECORD
