Metadata-Version: 2.1
Name: pytika
Version: 0.2.0
Summary: Apache Tika Server python client
License: MIT
Author: RamiAwar
Author-email: rami.awar.ra@gmail.com
Requires-Python: >=3.7,<4.0
Classifier: License :: OSI Approved :: MIT License
Classifier: Programming Language :: Python :: 3
Classifier: Programming Language :: Python :: 3.7
Classifier: Programming Language :: Python :: 3.8
Classifier: Programming Language :: Python :: 3.9
Classifier: Programming Language :: Python :: 3.10
Classifier: Programming Language :: Python :: 3.11
Requires-Dist: requests (>=2.28.2,<3.0.0)
Requires-Dist: typing-extensions (>=4.5.0,<5.0.0)
